fds/__init__.py
fds/sdk/__init__.py
fds/sdk/GlobalFilings/__init__.py
fds/sdk/GlobalFilings/api_client.py
fds/sdk/GlobalFilings/configuration.py
fds/sdk/GlobalFilings/exceptions.py
fds/sdk/GlobalFilings/model_utils.py
fds/sdk/GlobalFilings/rest.py
fds/sdk/GlobalFilings/api/__init__.py
fds/sdk/GlobalFilings/api/filings_api_api.py
fds/sdk/GlobalFilings/api/meta_api.py
fds/sdk/GlobalFilings/apis/__init__.py
fds/sdk/GlobalFilings/model/__init__.py
fds/sdk/GlobalFilings/model/category.py
fds/sdk/GlobalFilings/model/category_response.py
fds/sdk/GlobalFilings/model/count.py
fds/sdk/GlobalFilings/model/count_response.py
fds/sdk/GlobalFilings/model/document.py
fds/sdk/GlobalFilings/model/error_object.py
fds/sdk/GlobalFilings/model/error_response.py
fds/sdk/GlobalFilings/model/form_type.py
fds/sdk/GlobalFilings/model/form_type_response.py
fds/sdk/GlobalFilings/model/invalid_id_error_object.py
fds/sdk/GlobalFilings/model/search_response.py
fds/sdk/GlobalFilings/model/search_response_meta.py
fds/sdk/GlobalFilings/model/search_response_meta_pagination.py
fds/sdk/GlobalFilings/model/search_result.py
fds/sdk/GlobalFilings/model/source.py
fds/sdk/GlobalFilings/model/source_response.py
fds/sdk/GlobalFilings/model/time_zone.py
fds/sdk/GlobalFilings/model/time_zone_response.py
fds/sdk/GlobalFilings/models/__init__.py
fds_sdk_globalfilings-2.3.0.dist-info/licenses/LICENSE
fds_sdk_globalfilings-2.3.0.dist-info/METADATA
fds_sdk_globalfilings-2.3.0.dist-info/WHEEL
fds_sdk_globalfilings-2.3.0.dist-info/top_level.txt
fds_sdk_globalfilings-2.3.0.dist-info/RECORD
